advent_of_code.abi3.so
advent_of_code-2025.2.0.dist-info/RECORD
advent_of_code-2025.2.0.dist-info/WHEEL
advent_of_code-2025.2.0.dist-info/entry_points.txt
advent_of_code-2025.2.0.dist-info/top_level.txt
advent_of_code-2025.2.0.dist-info/METADATA
advent_of_code-2025.2.0.dist-info/licenses/LICENSE.txt
advent_of_code/__init__.pyi
advent_of_code/py.typed
advent_of_code_cli/main.py
