Metadata-Version: 2.4
Name: advent-of-code
Version: 2025.2.0
Home-page: https://github.com/fornwall/advent-of-code
License-File: LICENSE.txt
Dynamic: description
Dynamic: description-content-type
Dynamic: home-page
Dynamic: license-file
